pal/__init__.py
pal/_maths.py
pal/config.py
pal/contracts.py
pal/copulas.py
pal/couplings.py
pal/distributions.py
pal/frequency_severity.py
pal/maths.py
pal/py.typed
pal/stats.py
pal/stochastic_scalar.py
pal/types.py
pal/variables.py
proteusllp_actuarial_library-0.2.8.dist-info/METADATA
proteusllp_actuarial_library-0.2.8.dist-info/WHEEL
proteusllp_actuarial_library-0.2.8.dist-info/entry_points.txt
proteusllp_actuarial_library-0.2.8.dist-info/licenses/LICENSE
proteusllp_actuarial_library-0.2.8.dist-info/RECORD
