Metadata-Version: 2.1
Name: proteusllp-actuarial-library
Version: 0.2.8
Summary: Proteus Actuarial Library: A package for building and running stochastic actuarial models in Python.
Keywords: actuarial,insurance,capital
Author-Email: James Norman <james.norman@proteusllp.com>
Maintainer-Email: James Norman <james.norman@proteusllp.com>
License: MIT License
Classifier: Development Status :: 4 - Beta
Classifier: Intended Audience :: Financial and Insurance Industry
Classifier: License :: OSI Approved :: MIT License
Classifier: Programming Language :: Python :: 3
Classifier: Programming Language :: Python :: 3.13
Project-URL: Homepage, https://github.com/ProteusLLP/proteusllp-actuarial-library
Project-URL: Repository, https://github.com/ProteusLLP/proteusllp-actuarial-library
Project-URL: Issues, https://github.com/ProteusLLP/proteusllp-actuarial-library/issues
Project-URL: Documentation, https://proteusllp-actuarial-library.readthedocs.io/
Requires-Python: >=3.13
Requires-Dist: numpy>=2.2
Requires-Dist: scipy>=1.15
Requires-Dist: plotly>=6.0
Requires-Dist: pandas>=2.2
Requires-Dist: pandas-stubs>=2.3.0.250703
Requires-Dist: scipy-stubs>=1.16.0.2
Provides-Extra: gpu
Requires-Dist: cupy-cuda12x; extra == "gpu"
Provides-Extra: docs
Requires-Dist: sphinx>=8.2.3; extra == "docs"
Requires-Dist: sphinx-rtd-theme>=3.0.2; extra == "docs"
Requires-Dist: myst-parser>=4.0.1; extra == "docs"
Requires-Dist: sphinx-autodoc-typehints>=3.5.2; extra == "docs"
